Metadata-Version: 2.1
Name: info_entropy
Version: 0.5.3
Summary: info_entropy
Home-page: 
Author: 
Author-email: 
Keywords: info_entropy
Platform: any
